lgopy/__init__.py
lgopy/callbacks/__init__.py
lgopy/callbacks/callback.py
lgopy/core/__init__.py
lgopy/core/block.py
lgopy/core/block_builder.py
lgopy/core/block_mixin.py
lgopy/core/block_serializer.py
lgopy/core/pipeline.py
lgopy/core/registers.py
lgopy/core/stores/__init__.py
lgopy/core/stores/stores.py
lgopy/utils/__init__.py
lgopy/utils/build_utils.py
lgopy/utils/io_utils.py
lgopy/utils/lib_utils.py
lgopy/utils/singleton.py
lgopy-1.5.8.dist-info/METADATA
lgopy-1.5.8.dist-info/WHEEL
lgopy-1.5.8.dist-info/RECORD
