Metadata-Version: 2.4
Name: lgopy
Version: 1.5.8
Summary: LgoPy is an open-source library for building and createing multimodal data science pipelines.
Requires-Python: >=3.10
Requires-Dist: autoflake>=2.3.1
Requires-Dist: bandit>=1.7.9
Requires-Dist: black>=24.8.0
Requires-Dist: docker>=7.1.0
Requires-Dist: isort>=6.0.1
Requires-Dist: matplotlib>=3.9.2
Requires-Dist: multimethod>=1.12
Requires-Dist: pandas>=2.2.3
Requires-Dist: pydantic>=2.8.2
Requires-Dist: pylint>=3.2.7
Requires-Dist: python-dotenv>=1.0.1
Requires-Dist: ray[data,default,serve,train,tune]>=2.37.0
Requires-Dist: requests>=2.32.3
Requires-Dist: rich>=13.8.0
Requires-Dist: scikit-learn>=1.5.1
Requires-Dist: xarray>=2024.10.0
